pysin/__init__.py
pysin/extract.py
pysin/prescriptions_generator.py
pysin/search.py
pysin/mimic/__init__.py
pysin/mimic/attribute.py
pysin/mimic/attribute_type.py
pysin/mimic/cli.py
pysin/mimic/database_generator.py
pysin/mimic/example.py
pysin/mimic/mimic_preprocessing.py
pysin/mimic/table.py
pysin/utils/fonts/.DS_Store
pysin/utils/fonts/Airin.pkl
pysin/utils/fonts/Airin.ttf
pysin/utils/fonts/AlfridaDemoSignature.pkl
pysin/utils/fonts/AlfridaDemoSignature.ttf
pysin/utils/fonts/Allison Tessa Oblique.pkl
pysin/utils/fonts/Allison Tessa Oblique.ttf
pysin/utils/fonts/Almondita.pkl
pysin/utils/fonts/Almondita.ttf
pysin/utils/fonts/SCRIPTIN.pkl
pysin/utils/fonts/SCRIPTIN.ttf
pysin/utils/fonts/mayqueen.pkl
pysin/utils/fonts/mayqueen.ttf
pysin-1.6.1.dist-info/LICENSE.txt
pysin-1.6.1.dist-info/METADATA
pysin-1.6.1.dist-info/WHEEL
pysin-1.6.1.dist-info/entry_points.txt
pysin-1.6.1.dist-info/top_level.txt
pysin-1.6.1.dist-info/RECORD
